mastercardcurrencyconversion/__init__.py
mastercardcurrencyconversion/conversionrate.py
mastercardcurrencyconversion/currencies.py
mastercardcurrencyconversion/rateissued.py
mastercardcurrencyconversion/resourceconfig.py
mastercard_currency_client-2.0.0.dist-info/METADATA
mastercard_currency_client-2.0.0.dist-info/WHEEL
mastercard_currency_client-2.0.0.dist-info/RECORD
